yaml_config_tags/__init__.py
yaml_config_tags/loader.py
yaml_config_tags-0.5.0.dist-info/METADATA
yaml_config_tags-0.5.0.dist-info/WHEEL
yaml_config_tags-0.5.0.dist-info/RECORD
