Metadata-Version: 2.3
Name: yaml-config-tags
Version: 0.5.0
Summary: Custom tags to extend YAML for managing advanced configurations easily within a file. Environment variables, includes, and jinja templating.
License: MIT
Keywords: yaml,config
Author: Adrian Panella
Author-email: ianchi74@outlook.com
Requires-Python: >=3.11
Classifier: License :: OSI Approved :: MIT License
Classifier: Programming Language :: Python :: 3
Classifier: Programming Language :: Python :: 3.11
Classifier: Programming Language :: Python :: 3.12
Classifier: Programming Language :: Python :: 3.13
Requires-Dist: jinja2 (>=3.1.4,<4.0.0)
Requires-Dist: pyyaml (>=6.0.2,<7.0.0)
Project-URL: Documentation, https://github.com/ianchi/yaml-config-tags
Project-URL: Homepage, https://github.com/ianchi/yaml-config-tags
Project-URL: Repository, https://github.com/ianchi/yaml-config-tags.git
